{
    "name": "Ceisnoidhe Uladh",
    "attributes": {},
    "entities": [
        {
            "text": "Ceisnoidhe Uladh See Debility Of The Ulstermen"
        }
    ],
    "sources": [
        "Monaghan, Patricia. The Encyclopedia of Celtic Mythology and Folklore. Checkmark Books, 2008."
    ],
    "cyphertext": "_KUwIERYBNPEaezsgi-Vwt1iNRyyBugOFdymv3b-3S4Jo4zM7hKUojZRObDmN65f2dEqz950MxapHi1VPEWYvGLnUqbHCeBV7pnr-A==",
    "salt": "7FgUYwyQubOnOQ5nE_NzKw==",
    "text": "Ceisnoidhe Uladh See Debility Of The Ulstermen."
}