{
    "name": "Hellyas",
    "attributes": [
        {
            "entity": "Hellyas",
            "attribute": "minor figure"
        },
        {
            "entity": "Hellyas",
            "attribute": "ancestor of Lancelot"
        }
    ],
    "entities": [
        {
            "entity": "Hellyas",
            "type": "Arthurian hero"
        },
        {
            "entity": "Arthurian legend",
            "type": "legend"
        },
        {
            "entity": "Round Table",
            "type": "knight"
        },
        {
            "entity": "Lancelot",
            "type": "Round Table knight"
        }
    ],
    "sources": [
        "Monaghan, Patricia. The Encyclopedia of Celtic Mythology and Folklore. Checkmark Books, 2008."
    ],
    "cyphertext": "SZFvVwsaQ9cZUfiLMFRGcOGE6aO7PqbtI0PyJyDA_SXAhG7mqRhbhZPGqqkl99LpfldlxegdwGGrbmHoc6q-dElUxezLX8-GEEGlu9BNFjyjOsCefVBVtiIF0OwM9EkMrpkaYGLj6RbrkONQsHWt9-9AOghAPjWSgdRQx8fEdDA0AeI3AdNvW9coIW0KoQ==",
    "salt": "fmKnxb9J3Ir6FgcXTDgeXQ==",
    "text": "Arthurian hero Hellyas, though not a prominent character in the legend, held a significant position as he was the forefather of Lancelot, one of the knights of the Round Table."
}